{
  "cliente": "O Quintal Piri",
  "periodo": {
    "start": "2026-05-01",
    "end": "2026-05-31"
  },
  "gerado_em": "2026-06-03T16:12:14.408125",
  "consolidado": null,
  "meta": {
    "spend": 851.6,
    "reach": 31867,
    "impressions": 75764,
    "clicks": 1124,
    "cpm": 11.24,
    "cpc": 0.76,
    "ctr": 1.48,
    "frequency": 2.38,
    "campaigns": [
      {
        "name": "[CBO] [Z62 MAI/26] [ENGAJAMENTO]",
        "objective": "OUTCOME_ENGAGEMENT",
        "spend": 349.92,
        "reach": 6460,
        "impressions": 19739,
        "clicks": 311,
        "ctr": 1.58,
        "cpc": 1.13,
        "result_label": "Mensagens",
        "result_qty": 25,
        "result_cpr": 14.0
      },
      {
        "name": "[CBO] [TOPO PIRIDICAS] [TRAFEGO]",
        "objective": "LINK_CLICKS",
        "spend": 151.78,
        "reach": 13756,
        "impressions": 16907,
        "clicks": 556,
        "ctr": 3.29,
        "cpc": 0.27,
        "result_label": "Cliques",
        "result_qty": 412,
        "result_cpr": 0.37
      },
      {
        "name": "[CBO] [PAGODE 30/05] [ENGAJAMENTO]",
        "objective": "OUTCOME_ENGAGEMENT",
        "spend": 349.9,
        "reach": 15563,
        "impressions": 39118,
        "clicks": 257,
        "ctr": 0.66,
        "cpc": 1.36,
        "result_label": "Engajamentos",
        "result_qty": 11273,
        "result_cpr": 0.03
      }
    ],
    "ads": [
      {
        "name": "vd_z62_mai_26",
        "campaign": "[CBO] [Z62 MAI/26] [ENGAJAMENTO]",
        "spend": 349.92,
        "impressions": 19739,
        "clicks": 311,
        "ctr": 1.58,
        "cpc": 1.13,
        "frequency": 3.06,
        "result_label": "Mensagens",
        "result_qty": 25,
        "result_cpr": 14.0
      },
      {
        "name": "vd_piri_dicas",
        "campaign": "[CBO] [TOPO PIRIDICAS] [TRAFEGO]",
        "spend": 22.08,
        "impressions": 3053,
        "clicks": 70,
        "ctr": 2.29,
        "cpc": 0.32,
        "frequency": 1.07,
        "result_label": "Cliques",
        "result_qty": 53,
        "result_cpr": 0.42
      },
      {
        "name": "vd_piri_dicas_2",
        "campaign": "[CBO] [TOPO PIRIDICAS] [TRAFEGO]",
        "spend": 129.7,
        "impressions": 13854,
        "clicks": 486,
        "ctr": 3.51,
        "cpc": 0.27,
        "frequency": 1.22,
        "result_label": "Cliques",
        "result_qty": 359,
        "result_cpr": 0.36
      },
      {
        "name": "pagode_30_05",
        "campaign": "[CBO] [PAGODE 30/05] [ENGAJAMENTO]",
        "spend": 349.9,
        "impressions": 39118,
        "clicks": 257,
        "ctr": 0.66,
        "cpc": 1.36,
        "frequency": 2.51,
        "result_label": "Engajamentos",
        "result_qty": 11273,
        "result_cpr": 0.03
      }
    ]
  },
  "google": null,
  "ga4": null,
  "gmb": null
}